{
  "courses": [
    {
      "id": 1,
      "name": "project manager",
      "description": "ти навчишся керувати ІТ-проєктами та agile-командами",
      "pluses": [
        "2 проєкти в портфоліо",
        "hard skills",
        "soft skills"
      ],
      "possibilities": [
        "працевлаштуватися junior pm в it-компанію будь-якого рівня",
        "керувати та організовувати роботу команд за допомогою різних методик",
        "розставляти пріоритети та планувати завдання",
        "складати всю необхідну технічну документацію за проєктами",
        "правильно підбирати та мотивувати своїх командних граців",
        "керувати якістю виконуваного проєкта"
      ],
      "reviewsCount": 6,
      "img": "/images/hero-courses/course1.png"
    },
    {
      "id": 2,
      "name": "cybersecurity",
      "description": "ти навчишся створювати систему кіберзахисту застосунків",
      "pluses": [
        "4 проєкти в портфоліо",
        "hard skills"
      ],
      "possibilities": [
        "працевлаштуватися junior pm в it-компанію будь-якого рівня",
        "керувати та організовувати роботу команд за допомогою різних методик",
        "розставляти пріоритети та планувати завдання",
        "складати всю необхідну технічну документацію за проєктами",
        "правильно підбирати та мотивувати своїх командних граців",
        "керувати якістю виконуваного проєкта"
      ],
      "reviewsCount": 5,
      "img": "/images/hero-courses/course2.png"
    },
    {
      "id": 3,
      "name": "web developer",
      "description": "ти навчишся створювати сайти та вебзастосунки з нуля",
      "pluses": [
        "8 проєкти в портфоліо",
        "hard skills",
        "soft skills"
      ],
      "possibilities": [
        "працевлаштуватися junior pm в it-компанію будь-якого рівня",
        "керувати та організовувати роботу команд за допомогою різних методик",
        "розставляти пріоритети та планувати завдання",
        "складати всю необхідну технічну документацію за проєктами",
        "правильно підбирати та мотивувати своїх командних граців",
        "керувати якістю виконуваного проєкта"
      ],
      "reviewsCount": 4,
      "img": "/images/hero-courses/course3.png"
    },
    {
      "id": 4,
      "name": "smm specialist",
      "description": "Ти навчишся просувати бренди в соцмережах та налаштовувати рекламу",
      "pluses": [
        "2 проєкти в портфоліо",
        "hard skills",
        "soft skills"
      ],
      "possibilities": [
        "працевлаштуватися junior pm в it-компанію будь-якого рівня",
        "керувати та організовувати роботу команд за допомогою різних методик",
        "розставляти пріоритети та планувати завдання",
        "складати всю необхідну технічну документацію за проєктами",
        "правильно підбирати та мотивувати своїх командних граців",
        "керувати якістю виконуваного проєкта"
      ],
      "reviewsCount": 3,
      "img": "/images/hero-courses/course4.png"
    },
    {
      "id": 5,
      "name": "test engineer",
      "description": "ти навчишся тестувати вебсайти та мобільні застосунки",
      "pluses": [
        "2 проєкти в портфоліо",
        "hard skills",
        "soft skills"
      ],
      "possibilities": [
        "працевлаштуватися junior pm в it-компанію будь-якого рівня",
        "керувати та організовувати роботу команд за допомогою різних методик",
        "розставляти пріоритети та планувати завдання",
        "складати всю необхідну технічну документацію за проєктами",
        "правильно підбирати та мотивувати своїх командних граців",
        "керувати якістю виконуваного проєкта"
      ],
      "reviewsCount": 3,
      "img": "/images/hero-courses/course5.png"
    },
    {
      "id": 6,
      "name": "ux/ui designer",
      "description": "Ти навчишся створювати сайти та вебзастосунки з нуля",
      "pluses": [
        "2 проєкти в портфоліо",
        "hard skills",
        "soft skills"
      ],
      "possibilities": [
        "працевлаштуватися junior pm в it-компанію будь-якого рівня",
        "керувати та організовувати роботу команд за допомогою різних методик",
        "розставляти пріоритети та планувати завдання",
        "складати всю необхідну технічну документацію за проєктами",
        "правильно підбирати та мотивувати своїх командних граців",
        "керувати якістю виконуваного проєкта"
      ],
      "reviewsCount": 3,
      "img": "/images/hero-courses/course6.png"
    }
  ],
  "reviews": [
    {
      "courseId": 1,
      "text": "Чудовий курс, багато корисної інформації!"
    },
    {
      "courseId": 1,
      "text": "Інтерактивні заняття, які допомогли зрозуміти матеріал."
    },
    {
      "courseId": 1,
      "text": "Курс дуже практичний, отримав багато корисних навичок."
    },
    {
      "courseId": 1,
      "text": "Цікаві завдання, що дозволяють застосувати знання на практиці."
    },
    {
      "courseId": 1,
      "text": "Змістовний курс, який охоплює важливі аспекти проектного менеджменту."
    },
    {
      "courseId": 1,
      "text": "Рекомендую цей курс всім, хто хоче покращити свої навички в управлінні проектами."
    },
    {
      "courseId": 2,
      "text": "Цей курс допоміг мені розібратися в основах кібербезпеки."
    },
    {
      "courseId": 2,
      "text": "Дуже цікаво дізнатися, як захищати дані від хакерів."
    },
    {
      "courseId": 2,
      "text": "Практичні завдання допомагають краще розуміти теорію."
    },
    {
      "courseId": 2,
      "text": "Корисні поради щодо захисту від атак в Інтернеті."
    },
    {
      "courseId": 2,
      "text": "Завдяки цьому курсу я зрозумів основні принципи кібербезпеки."
    },
    {
      "courseId": 3,
      "text": "Курс дуже практичний і надає важливі знання для створення вебсайтів."
    },
    {
      "courseId": 3,
      "text": "Дуже корисний курс, якщо хочете стати веб-розробником."
    },
    {
      "courseId": 3,
      "text": "Вчитися створювати вебзастосунки стало набагато легше завдяки цьому курсу."
    },
    {
      "courseId": 3,
      "text": "Рекомендую цей курс усім, хто хоче навчитися розробляти сайти."
    },
    {
      "courseId": 4,
      "text": "Курс дуже інформативний, допомогло зрозуміти важливість SMM."
    },
    {
      "courseId": 4,
      "text": "Цікаво, як за допомогою соціальних мереж можна просувати бізнес."
    },
    {
      "courseId": 4,
      "text": "Курс охоплює всі основні аспекти SMM, корисно для початківців."
    },
    {
      "courseId": 5,
      "text": "Курс дуже детально охоплює основи тестування програмного забезпечення."
    },
    {
      "courseId": 5,
      "text": "Вчитися тестувати стало набагато простіше завдяки цьому курсу."
    },
    {
      "courseId": 5,
      "text": "Цей курс дає чітке розуміння, як тестувати вебсайти та мобільні додатки."
    },
    {
      "courseId": 6,
      "text": "Цей курс допоміг мені розібратися в основах UX/UI дизайну."
    },
    {
      "courseId": 6,
      "text": "Великий курс, який допоможе вам стати хорошим дизайнером."
    },
    {
      "courseId": 6,
      "text": "Це відмінний курс для тих, хто хоче навчитися створювати зручні інтерфейси."
    }
  ]
}